lucide/__init__.py
lucide/cli.py
lucide/config.py
lucide/core.py
lucide/data/__init__.py
lucide/data/lucide-icons.db
lucide/db.py
lucide/dev_utils.py
python_lucide-0.2.19.dist-info/WHEEL
python_lucide-0.2.19.dist-info/entry_points.txt
python_lucide-0.2.19.dist-info/METADATA
python_lucide-0.2.19.dist-info/RECORD
