Metadata-Version: 2.3
Name: python-lucide
Version: 0.2.19
Summary: A Python package for working with Lucide icons
Keywords: lucide,icons,svg,sqlite
Author: Mike Macpherson
License: MIT
Classifier: Development Status :: 4 - Beta
Classifier: Intended Audience :: Developers
Classifier: License :: OSI Approved :: MIT License
Classifier: Programming Language :: Python :: 3
Classifier: Programming Language :: Python :: 3.10
Classifier: Programming Language :: Python :: 3.11
Classifier: Programming Language :: Python :: 3.12
Classifier: Programming Language :: Python :: 3.13
Classifier: Programming Language :: Python :: 3.14
Classifier: Topic :: Software Development :: Libraries :: Python Modules
Requires-Python: >=3.10
Project-URL: Bug Tracker, https://github.com/mmacpherson/python-lucide/issues
Project-URL: Homepage, https://github.com/mmacpherson/python-lucide
Project-URL: Source Code, https://github.com/mmacpherson/python-lucide
